sync_composer/__init__.py
sync_composer/sync_composer.py
sync_composer-0.0.3.dist-info/LICENSE
sync_composer-0.0.3.dist-info/METADATA
sync_composer-0.0.3.dist-info/WHEEL
sync_composer-0.0.3.dist-info/top_level.txt
sync_composer-0.0.3.dist-info/RECORD
