Metadata-Version: 2.1
Name: sync-composer
Version: 0.0.3
Summary: sync composer and local
Home-page: https://github.com/paulhtremblay/composer_sync
Author: Henry Tremblay
Author-email: paulhtremblay@gmail.com
License: GNU GENERAL PUBLIC LICENSE
Classifier: Programming Language :: Python :: 3
Classifier: Topic :: Software Development :: Testing :: Mocking
License-File: LICENSE
